SHARE/__init__.py
SHARE/commandline.py
SHARE/generateConfessions.py
SHARE/gpt3-test.py
SHARE/meme_utils.py
SHARE/test.py
example_pkg_ralcanta-0.0.1.dist-info/LICENSE
example_pkg_ralcanta-0.0.1.dist-info/METADATA
example_pkg_ralcanta-0.0.1.dist-info/WHEEL
example_pkg_ralcanta-0.0.1.dist-info/top_level.txt
example_pkg_ralcanta-0.0.1.dist-info/RECORD
