Metadata-Version: 2.1
Name: example-pkg-ralcanta
Version: 0.0.1
Summary: Bot that posts witty, funny comments in MIT confessions
Home-page: https://github.com/ralcant/SHARE
Author: Raul Alcantara
Author-email: raulalfredoalcantara@gmail.com
License: UNKNOWN
Project-URL: Bug Tracker, https://github.com/ralcant/SHARE/issues
Platform: UNKNOWN
Classifier: Programming Language :: Python :: 3
Classifier: License :: OSI Approved :: MIT License
Classifier: Operating System :: OS Independent
Requires-Python: >=3.6
